fastsca/__init__.py
fastsca-0.0.1.dist-info/LICENSE
fastsca-0.0.1.dist-info/METADATA
fastsca-0.0.1.dist-info/WHEEL
fastsca-0.0.1.dist-info/top_level.txt
fastsca-0.0.1.dist-info/RECORD
