Metadata-Version: 2.1
Name: fastsca
Version: 0.0.1
Summary: fastsca
Home-page: https://github.com/aknay/fastsca
Author: Nay Aung Kyaw
Author-email: aknay@outlook.com
License: GPLv3
Classifier: Programming Language :: Python :: 3
Classifier: License :: OSI Approved :: GNU General Public License v3 (GPLv3)
Classifier: Operating System :: OS Independent
Requires-Python: >=3.6
License-File: LICENSE
Requires-Dist: numpy
Requires-Dist: h5py
Requires-Dist: matplotlib
Provides-Extra: dev
Requires-Dist: pytest ; extra == 'dev'
